odoo/addons/low_sold_product_report/README.rst
odoo/addons/low_sold_product_report/__init__.py
odoo/addons/low_sold_product_report/__manifest__.py
odoo/addons/low_sold_product_report/i18n/es.po
odoo/addons/low_sold_product_report/models/__init__.py
odoo/addons/low_sold_product_report/models/res_company.py
odoo/addons/low_sold_product_report/models/res_config_settings.py
odoo/addons/low_sold_product_report/readme/CONFIGURE.md
odoo/addons/low_sold_product_report/readme/CONTRIBUTORS.md
odoo/addons/low_sold_product_report/readme/DESCRIPTION.md
odoo/addons/low_sold_product_report/readme/USAGE.md
odoo/addons/low_sold_product_report/report/__init__.py
odoo/addons/low_sold_product_report/report/low_sold_product_report.py
odoo/addons/low_sold_product_report/report/low_sold_product_report_views.xml
odoo/addons/low_sold_product_report/security/ir.model.access.csv
odoo/addons/low_sold_product_report/security/low_sold_product_report_security.xml
odoo/addons/low_sold_product_report/static/description/icon.png
odoo/addons/low_sold_product_report/static/description/index.html
odoo/addons/low_sold_product_report/tests/__init__.py
odoo/addons/low_sold_product_report/tests/test_low_sold_product_report.py
odoo/addons/low_sold_product_report/views/res_config_settings_views.xml
odoo/addons/low_sold_product_report/wizards/__init__.py
odoo/addons/low_sold_product_report/wizards/low_sold_product_report_wizard.py
odoo/addons/low_sold_product_report/wizards/low_sold_product_report_wizard_views.xml
odoo_addon_low_sold_product_report-17.0.1.0.1.1.dist-info/METADATA
odoo_addon_low_sold_product_report-17.0.1.0.1.1.dist-info/WHEEL
odoo_addon_low_sold_product_report-17.0.1.0.1.1.dist-info/top_level.txt
odoo_addon_low_sold_product_report-17.0.1.0.1.1.dist-info/RECORD
