Metadata-Version: 2.1
Name: odoo-addon-low_sold_product_report
Version: 17.0.1.0.1.1
Requires-Python: >=3.10
Requires-Dist: odoo>=17.0a,<17.1dev
Summary: Adjustable Report of least sold product
Home-page: https://github.com/sygel-technology/sy-sale-reporting
License: AGPL-3
Author: Sygel, Odoo Community Association (OCA)
Author-email: support@odoo-community.org
Classifier: Programming Language :: Python
Classifier: Framework :: Odoo
Classifier: Framework :: Odoo :: 17.0
Classifier: License :: OSI Approved :: GNU Affero General Public License v3
